copyfilter/__init__.py
copyfilter/__main__.py
copyfilter-0.1.0.dist-info/METADATA
copyfilter-0.1.0.dist-info/WHEEL
copyfilter-0.1.0.dist-info/entry_points.txt
copyfilter-0.1.0.dist-info/RECORD
